optic/__init__.py
optic_document_flask-0.1.3.dist-info/LICENSE
optic_document_flask-0.1.3.dist-info/METADATA
optic_document_flask-0.1.3.dist-info/WHEEL
optic_document_flask-0.1.3.dist-info/top_level.txt
optic_document_flask-0.1.3.dist-info/RECORD
