Metadata-Version: 2.1
Name: optic-document-flask
Version: 0.1.3
Summary: Document a flask API with Optic
Home-page: https://github.com/opticdev/api-ingestion
Author: Optic
Author-email: acunniffe@gmail.com
License: MIT
Platform: UNKNOWN
Requires-Dist: flask
